[{"party": "Věci veřejné", "id": 1, "name": "Michal Bab\u00e1k", "search_query": "Michal+Bab\u00e1k"},
  {"party": "ANO", "id": 2, "name": "Andrej Babi\u0161", "search_query": "Andrej+Babi\u0161"},
  {"party": "Věci veřejné", "id": 3, "name": "V\u00edt B\u00e1rta", "search_query": "V\u00edt+B\u00e1rta"},
  {"party": "KDU-ČSL", "id": 4, "name": "Pavel B\u011blobr\u00e1dek", "search_query": "Pavel+B\u011blobr\u00e1dek"},
  {"party": "ODS", "id": 5, "name": "Petr Benda", "search_query": "Petr+Benda"},
  {"party": "ANO", "id": 6, "name": "Richard Brabec", "search_query": "Richard+Brabec"},
  {"party": "ANO", "id": 7, "name": "Tom\u00e1\u0161 B\u0159ezina", "search_query": "Tom\u00e1\u0161+B\u0159ezina"},
  {"party": "ODS", "id": 8, "name": "Franti\u0161ek D\u011bdi\u010d", "search_query": "Franti\u0161ek+D\u011bdi\u010d"},
  {"party": "ODS", "id": 9, "name": "Filip Dvo\u0159\u00e1k", "search_query": "Filip+Dvo\u0159\u00e1k"},
  {"party": "ANO", "id": 10, "name": "Jaroslav Falt\u00fdnek", "search_query": "Jaroslav+Falt\u00fdnek"},
  {"party": "ČSSD", "id": 11, "name": "Ji\u0159\u00ed Havl\u00ed\u010dek", "search_query": "Ji\u0159\u00ed+Havl\u00ed\u010dek"},
  {"party": "ODS", "id": 12, "name": "Petr Hejma", "search_query": "Petr+Hejma"},
  {"party": "KSČM", "id": 13, "name": "Jarom\u00edr Kohl\u00ed\u010dek", "search_query": "Jarom\u00edr+Kohl\u00ed\u010dek"},
  {"party": "TOP 09", "id": 14, "name": "Jaroslav Lobkowicz", "search_query": "Jaroslav+Lobkowicz"},
  {"party": "TOP 09", "id": 15, "name": "Old\u0159ich Lomeck\u00fd", "search_query": "Old\u0159ich+Lomeck\u00fd"},
  {"party": "ČSSD", "id": 16, "name": "Miloslav Ludv\u00edk", "search_query": "Miloslav+Ludv\u00edk"},
  {"party": "ANO", "id": 17, "name": "Marta Nov\u00e1kov\u00e1", "search_query": "Marta+Nov\u00e1kov\u00e1"},
  {"party": "ANO", "id": 18, "name": "Ivan Piln\u00fd", "search_query": "Ivan+Piln\u00fd"},
  {"party": "TOP 09", "id": 19, "name": "Ji\u0159\u00ed Posp\u00ed\u0161il", "search_query": "Ji\u0159\u00ed+Posp\u00ed\u0161il"},
  {"party": "ČSSD", "id": 20, "name": "Luk\u00e1\u0161 Semer\u00e1k", "search_query": "Luk\u00e1\u0161+Semer\u00e1k"},
  {"party": "ČSSD", "id": 21, "name": "Bohuslav Sobotka", "search_query": "Bohuslav+Sobotka"},
  {"party": "ANO", "id": 22, "name": "Dan \u0164ok", "search_query": "Dan+\u0164ok"},
  {"party": "ANO", "id": 23, "name": "Petr Vok\u0159\u00e1l", "search_query": "Petr+Vok\u0159\u00e1l"}]
  {"party": "ODS", "name": "Petr Fiala", "search_query": "Petr+Fiala"}